bt_api_py/__init__.py
bt_api_py/configs/__init__.py
bt_api_py/configs/account_config.yaml
bt_api_py/configs/account_config_example.yaml
bt_api_py/configs/binance_spot_symbol_info.pkl
bt_api_py/configs/binance_swap_symbol_info.pkl
bt_api_py/containers/__init__.py
bt_api_py/containers/accounts/__init__.py
bt_api_py/containers/accounts/account.py
bt_api_py/containers/accounts/binance_account.py
bt_api_py/containers/accounts/okx_account.py
bt_api_py/containers/balances/__init__.py
bt_api_py/containers/balances/balance.py
bt_api_py/containers/balances/binance_balance.py
bt_api_py/containers/balances/okx_balance.py
bt_api_py/containers/bars/__init__.py
bt_api_py/containers/bars/bar.py
bt_api_py/containers/bars/binance_bar.py
bt_api_py/containers/bars/okx_bar.py
bt_api_py/containers/exchanges/__init__.py
bt_api_py/containers/exchanges/binance_exchange_data.py
bt_api_py/containers/exchanges/exchange_data.py
bt_api_py/containers/exchanges/okx_exchange_data.py
bt_api_py/containers/fundingrates/__init__.py
bt_api_py/containers/fundingrates/binance_funding_rate.py
bt_api_py/containers/fundingrates/funding_rate.py
bt_api_py/containers/fundingrates/okx_funding_rate.py
bt_api_py/containers/incomes/__init__.py
bt_api_py/containers/incomes/binance_income.py
bt_api_py/containers/incomes/income.py
bt_api_py/containers/markprices/__init__.py
bt_api_py/containers/markprices/binance_mark_price.py
bt_api_py/containers/markprices/mark_price.py
bt_api_py/containers/markprices/okx_mark_price.py
bt_api_py/containers/orderbooks/__init__.py
bt_api_py/containers/orderbooks/binance_orderbook.py
bt_api_py/containers/orderbooks/okx_orderbook.py
bt_api_py/containers/orderbooks/orderbook.py
bt_api_py/containers/orders/__init__.py
bt_api_py/containers/orders/binance_order.py
bt_api_py/containers/orders/okx_order.py
bt_api_py/containers/orders/order.py
bt_api_py/containers/positions/__init__.py
bt_api_py/containers/positions/binance_position.py
bt_api_py/containers/positions/okx_position.py
bt_api_py-0.13.1.dist-info/METADATA
bt_api_py-0.13.1.dist-info/WHEEL
bt_api_py-0.13.1.dist-info/top_level.txt
bt_api_py-0.13.1.dist-info/RECORD
