Metadata-Version: 2.1
Name: bt_api_py
Version: 0.13.1
Summary: implement backtesting and trading of quantitative strategy
Home-page: https://github.com/cloudQuant/btpy
Author: cloudQuant
Author-email: yunjinqi@gmail.com
Classifier: Programming Language :: Python :: 3
Classifier: License :: OSI Approved :: MIT License
Requires-Dist: cython
Requires-Dist: numpy
